oab/__init__.py
oab/csv_output.py
oab/excel_output.py
oab/json_output.py
oab/library.py
oab/lzxd.py
oab/main.py
oab/properties.py
oab/table_output.py
oab-1.1.0.dist-info/LICENSE
oab-1.1.0.dist-info/METADATA
oab-1.1.0.dist-info/WHEEL
oab-1.1.0.dist-info/entry_points.txt
oab-1.1.0.dist-info/top_level.txt
oab-1.1.0.dist-info/RECORD
